aws_cdk/aws_lambda_rust/__init__.py
aws_cdk/aws_lambda_rust/py.typed
aws_cdk/aws_lambda_rust/_jsii/__init__.py
aws_cdk/aws_lambda_rust/_jsii/aws-lambda-rust@0.0.0.jsii.tgz
aws_cdk.aws_lambda_rust-0.0.0.dist-info/LICENSE
aws_cdk.aws_lambda_rust-0.0.0.dist-info/METADATA
aws_cdk.aws_lambda_rust-0.0.0.dist-info/WHEEL
aws_cdk.aws_lambda_rust-0.0.0.dist-info/top_level.txt
aws_cdk.aws_lambda_rust-0.0.0.dist-info/RECORD
